kahi_post_cleanup_entities/Kahi_post_cleanup_entities.py
kahi_post_cleanup_entities/__init__.py
kahi_post_cleanup_entities/_version.py
kahi_post_cleanup_entities-0.0.1a0.dist-info/LICENSE
kahi_post_cleanup_entities-0.0.1a0.dist-info/METADATA
kahi_post_cleanup_entities-0.0.1a0.dist-info/WHEEL
kahi_post_cleanup_entities-0.0.1a0.dist-info/top_level.txt
kahi_post_cleanup_entities-0.0.1a0.dist-info/RECORD
