Metadata-Version: 2.1
Name: kahi_post_cleanup_entities
Version: 0.0.1a0
Summary: Kahi plugin post cleanup entities
Home-page: https://github.com/colav/Kahi_plugins
Author: Colav
Author-email: colav@udea.edu.co
License: BSD
License-File: LICENSE
Requires-Dist: kahi
